src/__init__.py
src/main.py
src/server.py
code_interpreter_mcp_server-0.1.3.dist-info/METADATA
code_interpreter_mcp_server-0.1.3.dist-info/WHEEL
code_interpreter_mcp_server-0.1.3.dist-info/entry_points.txt
code_interpreter_mcp_server-0.1.3.dist-info/top_level.txt
code_interpreter_mcp_server-0.1.3.dist-info/RECORD
