Metadata-Version: 2.4
Name: code-interpreter-mcp-server
Version: 0.1.3
Summary: code-interpreter-mcp-server
Author-email: saikaNya <saikacat@outlook.com>
Requires-Python: >=3.11
Requires-Dist: mcp[cli]>=1.6.0
Requires-Dist: openpyxl>=3.1.5
Requires-Dist: pandas>=2.2.3
